dwnld/__init__.py
libdwnld/__init__.py
dwnld-0.2.1.dist-info/COPYING
dwnld-0.2.1.dist-info/WHEEL
dwnld-0.2.1.dist-info/METADATA
dwnld-0.2.1.dist-info/RECORD
