Metadata-Version: 2.1
Name: dwnld
Version: 0.2.1
Summary: A multiprotocol downloader
Home-page: https://github.com/4thel00z/dwnld
License: GPL-3
Author: 4thel00z
Author-email: 4thel00z@gmail.com
Requires-Python: >=3.7,<4.0
Classifier: License :: Other/Proprietary License
Classifier: Programming Language :: Python :: 3
Classifier: Programming Language :: Python :: 3.7
Classifier: Programming Language :: Python :: 3.8
Classifier: Programming Language :: Python :: 3.9
Requires-Dist: plumbum (>=1.7.0,<2.0.0)
Requires-Dist: requests (>=2.26.0,<3.0.0)
Requires-Dist: scp (>=0.13.6,<0.14.0)
Requires-Dist: torpy[requests] (>=1.1.6,<2.0.0)
